govdelivery/__init__.py
govdelivery/api.py
govdelivery/xml_payloads.py
govdelivery/xml_response_parsers.py
govdelivery/tests/__init__.py
govdelivery/tests/test_api.py
govdelivery/tests/test_test_utils.py
govdelivery/tests/test_xml_payloads.py
govdelivery/tests/test_xml_response_parsers.py
govdelivery/tests/utils.py
govdelivery-1.4.0.dist-info/LICENSE
govdelivery-1.4.0.dist-info/METADATA
govdelivery-1.4.0.dist-info/WHEEL
govdelivery-1.4.0.dist-info/top_level.txt
govdelivery-1.4.0.dist-info/RECORD
