Metadata-Version: 2.1
Name: govdelivery
Version: 1.4.0
Summary: Python module for interacting with the GovDelivery API
Home-page: https://github.com/cfpb/govdelivery
Author: CFPB
Author-email: tech@cfpb.gov
License: CC0
Platform: UNKNOWN
Classifier: Development Status :: 5 - Production/Stable
Classifier: Environment :: Web Environment
Classifier: Intended Audience :: Developers
Classifier: License :: CC0 1.0 Universal (CC0 1.0) Public Domain Dedication
Classifier: License :: Public Domain
Classifier: Natural Language :: English
Classifier: Operating System :: OS Independent
Classifier: Programming Language :: Python
Classifier: Programming Language :: Python :: 2.7
Classifier: Programming Language :: Python :: 3.6
Classifier: Topic :: Communications :: Email
Requires-Dist: requests (<3,>=2.22.0)
Provides-Extra: testing
Requires-Dist: coverage ; extra == 'testing'
Requires-Dist: responses ; extra == 'testing'
